<TRANSACTION>
<TYPE>income</TYPE>
<DESCRIPTION>Sold cards pack</DESCRIPTION>
<AMOUNT>10</AMOUNT>
<DATA_VALUE>1671408946</DATA_VALUE>
<DATA>Mon Dec 19 02:15:46 2022</DATA>
</TRANSACTION>

<TRANSACTION>
<TYPE>outcome</TYPE>
<DESCRIPTION>Lunch</DESCRIPTION>
<AMOUNT>5</AMOUNT>
<DATA_VALUE>1671408955</DATA_VALUE>
<DATA>Mon Dec 19 02:15:55 2022</DATA>
</TRANSACTION>

<TRANSACTION>
<TYPE>income</TYPE>
<DESCRIPTION>Gift from Mario</DESCRIPTION>
<AMOUNT>20</AMOUNT>
<DATA_VALUE>1671408995</DATA_VALUE>
<DATA>Mon Dec 19 02:16:35 2022</DATA>
</TRANSACTION>

<TRANSACTION>
<TYPE>outcome</TYPE>
<DESCRIPTION>New videogame</DESCRIPTION>
<AMOUNT>25</AMOUNT>
<DATA_VALUE>1671409005</DATA_VALUE>
<DATA>Mon Dec 19 02:16:45 2022</DATA>
</TRANSACTION>

<TRANSACTION>
<TYPE>income</TYPE>
<DESCRIPTION>Sold bedroom chair</DESCRIPTION>
<AMOUNT>35</AMOUNT>
<DATA_VALUE>1671409020</DATA_VALUE>
<DATA>Mon Dec 19 02:17:00 2022</DATA>
</TRANSACTION>

<TRANSACTION>
<TYPE>outcome</TYPE>
<DESCRIPTION>Dinner</DESCRIPTION>
<AMOUNT>10</AMOUNT>
<DATA_VALUE>1671409048</DATA_VALUE>
<DATA>Mon Dec 19 02:17:28 2022</DATA>
</TRANSACTION>